qapi_sdk/__init__.py
qapi_sdk/feed.py
qapi_sdk/logs/__init__.py
qapi_sdk/logs/logger.py
qapi_sdk/query.py
qapi_sdk/redshift.py
qapi_sdk-0.3.4.dist-info/WHEEL
qapi_sdk-0.3.4.dist-info/METADATA
qapi_sdk-0.3.4.dist-info/RECORD
