Metadata-Version: 2.1
Name: qapi-sdk
Version: 0.3.4
Summary: QAPI SDK provides a library of classes for working with Query API in your Python code.
Home-page: https://github.com/oneaudience/data-team-qapi-sdk
Author: TheBridgeDan
Author-email: 97176881+TheBridgeDan@users.noreply.github.com
Requires-Python: >=3.6,<4.0
Classifier: Programming Language :: Python :: 3
Classifier: Programming Language :: Python :: 3.10
Classifier: Programming Language :: Python :: 3.6
Classifier: Programming Language :: Python :: 3.7
Classifier: Programming Language :: Python :: 3.8
Classifier: Programming Language :: Python :: 3.9
Requires-Dist: boto3 (>=1.23.10,<2.0.0)
Requires-Dist: python-dotenv (>=0.20.0,<0.21.0)
Requires-Dist: requests (>=2.27.1,<3.0.0)
Requires-Dist: smart-open (>=6.0.0,<7.0.0)
Project-URL: Repository, https://github.com/oneaudience/data-team-qapi-sdk
